vmtool/__init__.py
vmtool/vm.py
VM_for_Dyte-1.0.0.dist-info/METADATA
VM_for_Dyte-1.0.0.dist-info/WHEEL
VM_for_Dyte-1.0.0.dist-info/entry_points.txt
VM_for_Dyte-1.0.0.dist-info/top_level.txt
VM_for_Dyte-1.0.0.dist-info/RECORD
