Metadata-Version: 2.1
Name: VM-for-Dyte
Version: 1.0.0
Summary: A simple lightweight cli tool that checks and updates dependency versions on all your node js github repos.
Home-page: https://github.com/dyte-submissions/dyte-vit-2022-aayush1607
Author: Aayush Chodvadiya
Author-email: auc1607@gmail.com
License: UNKNOWN
Platform: UNKNOWN
Classifier: Programming Language :: Python :: 3
Classifier: Operating System :: OS Independent
Requires-Dist: certifi (==2022.5.18.1)
Requires-Dist: charset-normalizer (==2.0.12)
Requires-Dist: idna (==3.3)
Requires-Dist: importlib-metadata (==4.11.4)
Requires-Dist: prettytable (==3.3.0)
Requires-Dist: requests (==2.27.1)
Requires-Dist: typing-extensions (==4.2.0)
Requires-Dist: urllib3 (==1.26.9)
Requires-Dist: wcwidth (==0.2.5)
Requires-Dist: zipp (==3.8.0)
